{
  "id": "rebecca-loviconi",
  "slug": "rebecca-loviconi",
  "year": 2026,
  "name": "Rebecca Loviconi",
  "pronouns": "sie/ihr",
  "role_de": "Filmmaker & Photojournalist",
  "role_en": "Filmmaker & Photojournalist",
  "organization": "For The Animals",
  "bio_de": "Rebecca Loviconi is an award-winning filmmaker and photojournalist based in Switzerland. Her work aims to empower people to become a line of defence for animals, planet and vulnerable communities. She has given over a hundred lectures internationally, including at the EU, Swiss and UK Parliaments.",
  "bio_en": "Rebecca Loviconi is an award-winning filmmaker and photojournalist based in Switzerland. Her work aims to empower people to become a line of defence for animals, planet and vulnerable communities. She has given over a hundred lectures internationally, including at the EU, Swiss and UK Parliaments.",
  "photo": "/images/speakers/Rebecca_Loviconi.jpg",
  "website": "https://www.letusbeheroes.com/",
  "social": {
    "instagram": "https://www.instagram.com/rlcappelli/"
  },
  "sessionIds": [
    "storytelling-for-animals"
  ],
  "sortOrder": 15
}
